{
  "service": "ssm",
  "community_support": true,
  "operations": [
    {
      "AddTagsToResource": {
        "implemented": true,
        "availability": "community",
        "internal_test_suite": false,
        "external_test_suite": false,
        "terraform_test_suite": false,
        "aws_validated": false,
        "snapshot_tested": false,
        "snapshot_skipped": ""
      }
    },
    {
      "AssociateOpsItemRelatedItem": {
        "implemented": false,
        "availability": "",
        "internal_test_suite": false,
        "external_test_suite": false,
        "terraform_test_suite": false,
        "aws_validated": false,
        "snapshot_tested": false,
        "snapshot_skipped": ""
      }
    },
    {
      "CancelCommand": {
        "implemented": false,
        "availability": "",
        "internal_test_suite": false,
        "external_test_suite": false,
        "terraform_test_suite": false,
        "aws_validated": false,
        "snapshot_tested": false,
        "snapshot_skipped": ""
      }
    },
    {
      "CancelMaintenanceWindowExecution": {
        "implemented": false,
        "availability": "",
        "internal_test_suite": false,
        "external_test_suite": false,
        "terraform_test_suite": false,
        "aws_validated": false,
        "snapshot_tested": false,
        "snapshot_skipped": ""
      }
    },
    {
      "CreateActivation": {
        "implemented": false,
        "availability": "",
        "internal_test_suite": false,
        "external_test_suite": false,
        "terraform_test_suite": false,
        "aws_validated": false,
        "snapshot_tested": false,
        "snapshot_skipped": ""
      }
    },
    {
      "CreateAssociation": {
        "implemented": false,
        "availability": "",
        "internal_test_suite": false,
        "external_test_suite": false,
        "terraform_test_suite": false,
        "aws_validated": false,
        "snapshot_tested": false,
        "snapshot_skipped": ""
      }
    },
    {
      "CreateAssociationBatch": {
        "implemented": false,
        "availability": "",
        "internal_test_suite": false,
        "external_test_suite": false,
        "terraform_test_suite": false,
        "aws_validated": false,
        "snapshot_tested": false,
        "snapshot_skipped": ""
      }
    },
    {
      "CreateDocument": {
        "implemented": true,
        "availability": "community",
        "internal_test_suite": false,
        "external_test_suite": false,
        "terraform_test_suite": false,
        "aws_validated": false,
        "snapshot_tested": false,
        "snapshot_skipped": ""
      }
    },
    {
      "CreateMaintenanceWindow": {
        "implemented": true,
        "availability": "community",
        "internal_test_suite": false,
        "external_test_suite": false,
        "terraform_test_suite": false,
        "aws_validated": false,
        "snapshot_tested": false,
        "snapshot_skipped": ""
      }
    },
    {
      "CreateOpsItem": {
        "implemented": false,
        "availability": "",
        "internal_test_suite": false,
        "external_test_suite": false,
        "terraform_test_suite": false,
        "aws_validated": false,
        "snapshot_tested": false,
        "snapshot_skipped": ""
      }
    },
    {
      "CreateOpsMetadata": {
        "implemented": false,
        "availability": "",
        "internal_test_suite": false,
        "external_test_suite": false,
        "terraform_test_suite": false,
        "aws_validated": false,
        "snapshot_tested": false,
        "snapshot_skipped": ""
      }
    },
    {
      "CreatePatchBaseline": {
        "implemented": true,
        "availability": "community",
        "internal_test_suite": false,
        "external_test_suite": false,
        "terraform_test_suite": false,
        "aws_validated": false,
        "snapshot_tested": false,
        "snapshot_skipped": ""
      }
    },
    {
      "CreateResourceDataSync": {
        "implemented": false,
        "availability": "",
        "internal_test_suite": false,
        "external_test_suite": false,
        "terraform_test_suite": false,
        "aws_validated": false,
        "snapshot_tested": false,
        "snapshot_skipped": ""
      }
    },
    {
      "DeleteActivation": {
        "implemented": false,
        "availability": "",
        "internal_test_suite": false,
        "external_test_suite": false,
        "terraform_test_suite": false,
        "aws_validated": false,
        "snapshot_tested": false,
        "snapshot_skipped": ""
      }
    },
    {
      "DeleteAssociation": {
        "implemented": false,
        "availability": "",
        "internal_test_suite": false,
        "external_test_suite": false,
        "terraform_test_suite": false,
        "aws_validated": false,
        "snapshot_tested": false,
        "snapshot_skipped": ""
      }
    },
    {
      "DeleteDocument": {
        "implemented": true,
        "availability": "community",
        "internal_test_suite": false,
        "external_test_suite": false,
        "terraform_test_suite": false,
        "aws_validated": false,
        "snapshot_tested": false,
        "snapshot_skipped": ""
      }
    },
    {
      "DeleteInventory": {
        "implemented": false,
        "availability": "",
        "internal_test_suite": false,
        "external_test_suite": false,
        "terraform_test_suite": false,
        "aws_validated": false,
        "snapshot_tested": false,
        "snapshot_skipped": ""
      }
    },
    {
      "DeleteMaintenanceWindow": {
        "implemented": true,
        "availability": "community",
        "internal_test_suite": false,
        "external_test_suite": false,
        "terraform_test_suite": false,
        "aws_validated": false,
        "snapshot_tested": false,
        "snapshot_skipped": ""
      }
    },
    {
      "DeleteOpsItem": {
        "implemented": false,
        "availability": "",
        "internal_test_suite": false,
        "external_test_suite": false,
        "terraform_test_suite": false,
        "aws_validated": false,
        "snapshot_tested": false,
        "snapshot_skipped": ""
      }
    },
    {
      "DeleteOpsMetadata": {
        "implemented": false,
        "availability": "",
        "internal_test_suite": false,
        "external_test_suite": false,
        "terraform_test_suite": false,
        "aws_validated": false,
        "snapshot_tested": false,
        "snapshot_skipped": ""
      }
    },
    {
      "DeleteParameter": {
        "implemented": true,
        "availability": "community",
        "internal_test_suite": false,
        "external_test_suite": false,
        "terraform_test_suite": false,
        "aws_validated": false,
        "snapshot_tested": false,
        "snapshot_skipped": ""
      }
    },
    {
      "DeleteParameters": {
        "implemented": true,
        "availability": "community",
        "internal_test_suite": false,
        "external_test_suite": false,
        "terraform_test_suite": false,
        "aws_validated": false,
        "snapshot_tested": false,
        "snapshot_skipped": ""
      }
    },
    {
      "DeletePatchBaseline": {
        "implemented": true,
        "availability": "community",
        "internal_test_suite": false,
        "external_test_suite": false,
        "terraform_test_suite": false,
        "aws_validated": false,
        "snapshot_tested": false,
        "snapshot_skipped": ""
      }
    },
    {
      "DeleteResourceDataSync": {
        "implemented": false,
        "availability": "",
        "internal_test_suite": false,
        "external_test_suite": false,
        "terraform_test_suite": false,
        "aws_validated": false,
        "snapshot_tested": false,
        "snapshot_skipped": ""
      }
    },
    {
      "DeleteResourcePolicy": {
        "implemented": false,
        "availability": "",
        "internal_test_suite": false,
        "external_test_suite": false,
        "terraform_test_suite": false,
        "aws_validated": false,
        "snapshot_tested": false,
        "snapshot_skipped": ""
      }
    },
    {
      "DeregisterManagedInstance": {
        "implemented": false,
        "availability": "",
        "internal_test_suite": false,
        "external_test_suite": false,
        "terraform_test_suite": false,
        "aws_validated": false,
        "snapshot_tested": false,
        "snapshot_skipped": ""
      }
    },
    {
      "DeregisterPatchBaselineForPatchGroup": {
        "implemented": false,
        "availability": "",
        "internal_test_suite": false,
        "external_test_suite": false,
        "terraform_test_suite": false,
        "aws_validated": false,
        "snapshot_tested": false,
        "snapshot_skipped": ""
      }
    },
    {
      "DeregisterTargetFromMaintenanceWindow": {
        "implemented": true,
        "availability": "community",
        "internal_test_suite": false,
        "external_test_suite": false,
        "terraform_test_suite": false,
        "aws_validated": false,
        "snapshot_tested": false,
        "snapshot_skipped": ""
      }
    },
    {
      "DeregisterTaskFromMaintenanceWindow": {
        "implemented": true,
        "availability": "community",
        "internal_test_suite": false,
        "external_test_suite": false,
        "terraform_test_suite": false,
        "aws_validated": false,
        "snapshot_tested": false,
        "snapshot_skipped": ""
      }
    },
    {
      "DescribeActivations": {
        "implemented": false,
        "availability": "",
        "internal_test_suite": false,
        "external_test_suite": false,
        "terraform_test_suite": false,
        "aws_validated": false,
        "snapshot_tested": false,
        "snapshot_skipped": ""
      }
    },
    {
      "DescribeAssociation": {
        "implemented": false,
        "availability": "",
        "internal_test_suite": false,
        "external_test_suite": false,
        "terraform_test_suite": false,
        "aws_validated": false,
        "snapshot_tested": false,
        "snapshot_skipped": ""
      }
    },
    {
      "DescribeAssociationExecutionTargets": {
        "implemented": false,
        "availability": "",
        "internal_test_suite": false,
        "external_test_suite": false,
        "terraform_test_suite": false,
        "aws_validated": false,
        "snapshot_tested": false,
        "snapshot_skipped": ""
      }
    },
    {
      "DescribeAssociationExecutions": {
        "implemented": false,
        "availability": "",
        "internal_test_suite": false,
        "external_test_suite": false,
        "terraform_test_suite": false,
        "aws_validated": false,
        "snapshot_tested": false,
        "snapshot_skipped": ""
      }
    },
    {
      "DescribeAutomationExecutions": {
        "implemented": false,
        "availability": "",
        "internal_test_suite": false,
        "external_test_suite": false,
        "terraform_test_suite": false,
        "aws_validated": false,
        "snapshot_tested": false,
        "snapshot_skipped": ""
      }
    },
    {
      "DescribeAutomationStepExecutions": {
        "implemented": false,
        "availability": "",
        "internal_test_suite": false,
        "external_test_suite": false,
        "terraform_test_suite": false,
        "aws_validated": false,
        "snapshot_tested": false,
        "snapshot_skipped": ""
      }
    },
    {
      "DescribeAvailablePatches": {
        "implemented": false,
        "availability": "",
        "internal_test_suite": false,
        "external_test_suite": false,
        "terraform_test_suite": false,
        "aws_validated": false,
        "snapshot_tested": false,
        "snapshot_skipped": ""
      }
    },
    {
      "DescribeDocument": {
        "implemented": true,
        "availability": "community",
        "internal_test_suite": false,
        "external_test_suite": false,
        "terraform_test_suite": false,
        "aws_validated": false,
        "snapshot_tested": false,
        "snapshot_skipped": ""
      }
    },
    {
      "DescribeDocumentPermission": {
        "implemented": true,
        "availability": "community",
        "internal_test_suite": false,
        "external_test_suite": false,
        "terraform_test_suite": false,
        "aws_validated": false,
        "snapshot_tested": false,
        "snapshot_skipped": ""
      }
    },
    {
      "DescribeEffectiveInstanceAssociations": {
        "implemented": false,
        "availability": "",
        "internal_test_suite": false,
        "external_test_suite": false,
        "terraform_test_suite": false,
        "aws_validated": false,
        "snapshot_tested": false,
        "snapshot_skipped": ""
      }
    },
    {
      "DescribeEffectivePatchesForPatchBaseline": {
        "implemented": false,
        "availability": "",
        "internal_test_suite": false,
        "external_test_suite": false,
        "terraform_test_suite": false,
        "aws_validated": false,
        "snapshot_tested": false,
        "snapshot_skipped": ""
      }
    },
    {
      "DescribeInstanceAssociationsStatus": {
        "implemented": false,
        "availability": "",
        "internal_test_suite": false,
        "external_test_suite": false,
        "terraform_test_suite": false,
        "aws_validated": false,
        "snapshot_tested": false,
        "snapshot_skipped": ""
      }
    },
    {
      "DescribeInstanceInformation": {
        "implemented": false,
        "availability": "",
        "internal_test_suite": false,
        "external_test_suite": false,
        "terraform_test_suite": false,
        "aws_validated": false,
        "snapshot_tested": false,
        "snapshot_skipped": ""
      }
    },
    {
      "DescribeInstancePatchStates": {
        "implemented": false,
        "availability": "",
        "internal_test_suite": false,
        "external_test_suite": false,
        "terraform_test_suite": false,
        "aws_validated": false,
        "snapshot_tested": false,
        "snapshot_skipped": ""
      }
    },
    {
      "DescribeInstancePatchStatesForPatchGroup": {
        "implemented": false,
        "availability": "",
        "internal_test_suite": false,
        "external_test_suite": false,
        "terraform_test_suite": false,
        "aws_validated": false,
        "snapshot_tested": false,
        "snapshot_skipped": ""
      }
    },
    {
      "DescribeInstancePatches": {
        "implemented": false,
        "availability": "",
        "internal_test_suite": false,
        "external_test_suite": false,
        "terraform_test_suite": false,
        "aws_validated": false,
        "snapshot_tested": false,
        "snapshot_skipped": ""
      }
    },
    {
      "DescribeInstanceProperties": {
        "implemented": false,
        "availability": "",
        "internal_test_suite": false,
        "external_test_suite": false,
        "terraform_test_suite": false,
        "aws_validated": false,
        "snapshot_tested": false,
        "snapshot_skipped": ""
      }
    },
    {
      "DescribeInventoryDeletions": {
        "implemented": false,
        "availability": "",
        "internal_test_suite": false,
        "external_test_suite": false,
        "terraform_test_suite": false,
        "aws_validated": false,
        "snapshot_tested": false,
        "snapshot_skipped": ""
      }
    },
    {
      "DescribeMaintenanceWindowExecutionTaskInvocations": {
        "implemented": false,
        "availability": "",
        "internal_test_suite": false,
        "external_test_suite": false,
        "terraform_test_suite": false,
        "aws_validated": false,
        "snapshot_tested": false,
        "snapshot_skipped": ""
      }
    },
    {
      "DescribeMaintenanceWindowExecutionTasks": {
        "implemented": false,
        "availability": "",
        "internal_test_suite": false,
        "external_test_suite": false,
        "terraform_test_suite": false,
        "aws_validated": false,
        "snapshot_tested": false,
        "snapshot_skipped": ""
      }
    },
    {
      "DescribeMaintenanceWindowExecutions": {
        "implemented": false,
        "availability": "",
        "internal_test_suite": false,
        "external_test_suite": false,
        "terraform_test_suite": false,
        "aws_validated": false,
        "snapshot_tested": false,
        "snapshot_skipped": ""
      }
    },
    {
      "DescribeMaintenanceWindowSchedule": {
        "implemented": false,
        "availability": "",
        "internal_test_suite": false,
        "external_test_suite": false,
        "terraform_test_suite": false,
        "aws_validated": false,
        "snapshot_tested": false,
        "snapshot_skipped": ""
      }
    },
    {
      "DescribeMaintenanceWindowTargets": {
        "implemented": true,
        "availability": "community",
        "internal_test_suite": false,
        "external_test_suite": false,
        "terraform_test_suite": false,
        "aws_validated": false,
        "snapshot_tested": false,
        "snapshot_skipped": ""
      }
    },
    {
      "DescribeMaintenanceWindowTasks": {
        "implemented": true,
        "availability": "community",
        "internal_test_suite": false,
        "external_test_suite": false,
        "terraform_test_suite": false,
        "aws_validated": false,
        "snapshot_tested": false,
        "snapshot_skipped": ""
      }
    },
    {
      "DescribeMaintenanceWindows": {
        "implemented": true,
        "availability": "community",
        "internal_test_suite": false,
        "external_test_suite": false,
        "terraform_test_suite": false,
        "aws_validated": false,
        "snapshot_tested": false,
        "snapshot_skipped": ""
      }
    },
    {
      "DescribeMaintenanceWindowsForTarget": {
        "implemented": false,
        "availability": "",
        "internal_test_suite": false,
        "external_test_suite": false,
        "terraform_test_suite": false,
        "aws_validated": false,
        "snapshot_tested": false,
        "snapshot_skipped": ""
      }
    },
    {
      "DescribeOpsItems": {
        "implemented": false,
        "availability": "",
        "internal_test_suite": false,
        "external_test_suite": false,
        "terraform_test_suite": false,
        "aws_validated": false,
        "snapshot_tested": false,
        "snapshot_skipped": ""
      }
    },
    {
      "DescribeParameters": {
        "implemented": true,
        "availability": "community",
        "internal_test_suite": false,
        "external_test_suite": false,
        "terraform_test_suite": false,
        "aws_validated": false,
        "snapshot_tested": false,
        "snapshot_skipped": ""
      }
    },
    {
      "DescribePatchBaselines": {
        "implemented": true,
        "availability": "community",
        "internal_test_suite": false,
        "external_test_suite": false,
        "terraform_test_suite": false,
        "aws_validated": false,
        "snapshot_tested": false,
        "snapshot_skipped": ""
      }
    },
    {
      "DescribePatchGroupState": {
        "implemented": false,
        "availability": "",
        "internal_test_suite": false,
        "external_test_suite": false,
        "terraform_test_suite": false,
        "aws_validated": false,
        "snapshot_tested": false,
        "snapshot_skipped": ""
      }
    },
    {
      "DescribePatchGroups": {
        "implemented": false,
        "availability": "",
        "internal_test_suite": false,
        "external_test_suite": false,
        "terraform_test_suite": false,
        "aws_validated": false,
        "snapshot_tested": false,
        "snapshot_skipped": ""
      }
    },
    {
      "DescribePatchProperties": {
        "implemented": false,
        "availability": "",
        "internal_test_suite": false,
        "external_test_suite": false,
        "terraform_test_suite": false,
        "aws_validated": false,
        "snapshot_tested": false,
        "snapshot_skipped": ""
      }
    },
    {
      "DescribeSessions": {
        "implemented": false,
        "availability": "",
        "internal_test_suite": false,
        "external_test_suite": false,
        "terraform_test_suite": false,
        "aws_validated": false,
        "snapshot_tested": false,
        "snapshot_skipped": ""
      }
    },
    {
      "DisassociateOpsItemRelatedItem": {
        "implemented": false,
        "availability": "",
        "internal_test_suite": false,
        "external_test_suite": false,
        "terraform_test_suite": false,
        "aws_validated": false,
        "snapshot_tested": false,
        "snapshot_skipped": ""
      }
    },
    {
      "GetAccessToken": {
        "implemented": false,
        "availability": "",
        "internal_test_suite": false,
        "external_test_suite": false,
        "terraform_test_suite": false,
        "aws_validated": false,
        "snapshot_tested": false,
        "snapshot_skipped": ""
      }
    },
    {
      "GetAutomationExecution": {
        "implemented": false,
        "availability": "",
        "internal_test_suite": false,
        "external_test_suite": false,
        "terraform_test_suite": false,
        "aws_validated": false,
        "snapshot_tested": false,
        "snapshot_skipped": ""
      }
    },
    {
      "GetCalendarState": {
        "implemented": false,
        "availability": "",
        "internal_test_suite": false,
        "external_test_suite": false,
        "terraform_test_suite": false,
        "aws_validated": false,
        "snapshot_tested": false,
        "snapshot_skipped": ""
      }
    },
    {
      "GetCommandInvocation": {
        "implemented": true,
        "availability": "community",
        "internal_test_suite": false,
        "external_test_suite": false,
        "terraform_test_suite": false,
        "aws_validated": false,
        "snapshot_tested": false,
        "snapshot_skipped": ""
      }
    },
    {
      "GetConnectionStatus": {
        "implemented": false,
        "availability": "",
        "internal_test_suite": false,
        "external_test_suite": false,
        "terraform_test_suite": false,
        "aws_validated": false,
        "snapshot_tested": false,
        "snapshot_skipped": ""
      }
    },
    {
      "GetDefaultPatchBaseline": {
        "implemented": false,
        "availability": "",
        "internal_test_suite": false,
        "external_test_suite": false,
        "terraform_test_suite": false,
        "aws_validated": false,
        "snapshot_tested": false,
        "snapshot_skipped": ""
      }
    },
    {
      "GetDeployablePatchSnapshotForInstance": {
        "implemented": false,
        "availability": "",
        "internal_test_suite": false,
        "external_test_suite": false,
        "terraform_test_suite": false,
        "aws_validated": false,
        "snapshot_tested": false,
        "snapshot_skipped": ""
      }
    },
    {
      "GetDocument": {
        "implemented": true,
        "availability": "community",
        "internal_test_suite": false,
        "external_test_suite": false,
        "terraform_test_suite": false,
        "aws_validated": false,
        "snapshot_tested": false,
        "snapshot_skipped": ""
      }
    },
    {
      "GetExecutionPreview": {
        "implemented": false,
        "availability": "",
        "internal_test_suite": false,
        "external_test_suite": false,
        "terraform_test_suite": false,
        "aws_validated": false,
        "snapshot_tested": false,
        "snapshot_skipped": ""
      }
    },
    {
      "GetInventory": {
        "implemented": false,
        "availability": "",
        "internal_test_suite": false,
        "external_test_suite": false,
        "terraform_test_suite": false,
        "aws_validated": false,
        "snapshot_tested": false,
        "snapshot_skipped": ""
      }
    },
    {
      "GetInventorySchema": {
        "implemented": false,
        "availability": "",
        "internal_test_suite": false,
        "external_test_suite": false,
        "terraform_test_suite": false,
        "aws_validated": false,
        "snapshot_tested": false,
        "snapshot_skipped": ""
      }
    },
    {
      "GetMaintenanceWindow": {
        "implemented": true,
        "availability": "community",
        "internal_test_suite": false,
        "external_test_suite": false,
        "terraform_test_suite": false,
        "aws_validated": false,
        "snapshot_tested": false,
        "snapshot_skipped": ""
      }
    },
    {
      "GetMaintenanceWindowExecution": {
        "implemented": false,
        "availability": "",
        "internal_test_suite": false,
        "external_test_suite": false,
        "terraform_test_suite": false,
        "aws_validated": false,
        "snapshot_tested": false,
        "snapshot_skipped": ""
      }
    },
    {
      "GetMaintenanceWindowExecutionTask": {
        "implemented": false,
        "availability": "",
        "internal_test_suite": false,
        "external_test_suite": false,
        "terraform_test_suite": false,
        "aws_validated": false,
        "snapshot_tested": false,
        "snapshot_skipped": ""
      }
    },
    {
      "GetMaintenanceWindowExecutionTaskInvocation": {
        "implemented": false,
        "availability": "",
        "internal_test_suite": false,
        "external_test_suite": false,
        "terraform_test_suite": false,
        "aws_validated": false,
        "snapshot_tested": false,
        "snapshot_skipped": ""
      }
    },
    {
      "GetMaintenanceWindowTask": {
        "implemented": false,
        "availability": "",
        "internal_test_suite": false,
        "external_test_suite": false,
        "terraform_test_suite": false,
        "aws_validated": false,
        "snapshot_tested": false,
        "snapshot_skipped": ""
      }
    },
    {
      "GetOpsItem": {
        "implemented": false,
        "availability": "",
        "internal_test_suite": false,
        "external_test_suite": false,
        "terraform_test_suite": false,
        "aws_validated": false,
        "snapshot_tested": false,
        "snapshot_skipped": ""
      }
    },
    {
      "GetOpsMetadata": {
        "implemented": false,
        "availability": "",
        "internal_test_suite": false,
        "external_test_suite": false,
        "terraform_test_suite": false,
        "aws_validated": false,
        "snapshot_tested": false,
        "snapshot_skipped": ""
      }
    },
    {
      "GetOpsSummary": {
        "implemented": false,
        "availability": "",
        "internal_test_suite": false,
        "external_test_suite": false,
        "terraform_test_suite": false,
        "aws_validated": false,
        "snapshot_tested": false,
        "snapshot_skipped": ""
      }
    },
    {
      "GetParameter": {
        "implemented": true,
        "availability": "community",
        "internal_test_suite": false,
        "external_test_suite": false,
        "terraform_test_suite": false,
        "aws_validated": false,
        "snapshot_tested": false,
        "snapshot_skipped": ""
      }
    },
    {
      "GetParameterHistory": {
        "implemented": true,
        "availability": "community",
        "internal_test_suite": false,
        "external_test_suite": false,
        "terraform_test_suite": false,
        "aws_validated": false,
        "snapshot_tested": false,
        "snapshot_skipped": ""
      }
    },
    {
      "GetParameters": {
        "implemented": true,
        "availability": "community",
        "internal_test_suite": false,
        "external_test_suite": false,
        "terraform_test_suite": false,
        "aws_validated": false,
        "snapshot_tested": false,
        "snapshot_skipped": ""
      }
    },
    {
      "GetParametersByPath": {
        "implemented": true,
        "availability": "community",
        "internal_test_suite": false,
        "external_test_suite": false,
        "terraform_test_suite": false,
        "aws_validated": false,
        "snapshot_tested": false,
        "snapshot_skipped": ""
      }
    },
    {
      "GetPatchBaseline": {
        "implemented": false,
        "availability": "",
        "internal_test_suite": false,
        "external_test_suite": false,
        "terraform_test_suite": false,
        "aws_validated": false,
        "snapshot_tested": false,
        "snapshot_skipped": ""
      }
    },
    {
      "GetPatchBaselineForPatchGroup": {
        "implemented": false,
        "availability": "",
        "internal_test_suite": false,
        "external_test_suite": false,
        "terraform_test_suite": false,
        "aws_validated": false,
        "snapshot_tested": false,
        "snapshot_skipped": ""
      }
    },
    {
      "GetResourcePolicies": {
        "implemented": false,
        "availability": "",
        "internal_test_suite": false,
        "external_test_suite": false,
        "terraform_test_suite": false,
        "aws_validated": false,
        "snapshot_tested": false,
        "snapshot_skipped": ""
      }
    },
    {
      "GetServiceSetting": {
        "implemented": false,
        "availability": "",
        "internal_test_suite": false,
        "external_test_suite": false,
        "terraform_test_suite": false,
        "aws_validated": false,
        "snapshot_tested": false,
        "snapshot_skipped": ""
      }
    },
    {
      "LabelParameterVersion": {
        "implemented": true,
        "availability": "community",
        "internal_test_suite": false,
        "external_test_suite": false,
        "terraform_test_suite": false,
        "aws_validated": false,
        "snapshot_tested": false,
        "snapshot_skipped": ""
      }
    },
    {
      "ListAssociationVersions": {
        "implemented": false,
        "availability": "",
        "internal_test_suite": false,
        "external_test_suite": false,
        "terraform_test_suite": false,
        "aws_validated": false,
        "snapshot_tested": false,
        "snapshot_skipped": ""
      }
    },
    {
      "ListAssociations": {
        "implemented": false,
        "availability": "",
        "internal_test_suite": false,
        "external_test_suite": false,
        "terraform_test_suite": false,
        "aws_validated": false,
        "snapshot_tested": false,
        "snapshot_skipped": ""
      }
    },
    {
      "ListCommandInvocations": {
        "implemented": false,
        "availability": "",
        "internal_test_suite": false,
        "external_test_suite": false,
        "terraform_test_suite": false,
        "aws_validated": false,
        "snapshot_tested": false,
        "snapshot_skipped": ""
      }
    },
    {
      "ListCommands": {
        "implemented": true,
        "availability": "community",
        "internal_test_suite": false,
        "external_test_suite": false,
        "terraform_test_suite": false,
        "aws_validated": false,
        "snapshot_tested": false,
        "snapshot_skipped": ""
      }
    },
    {
      "ListComplianceItems": {
        "implemented": false,
        "availability": "",
        "internal_test_suite": false,
        "external_test_suite": false,
        "terraform_test_suite": false,
        "aws_validated": false,
        "snapshot_tested": false,
        "snapshot_skipped": ""
      }
    },
    {
      "ListComplianceSummaries": {
        "implemented": false,
        "availability": "",
        "internal_test_suite": false,
        "external_test_suite": false,
        "terraform_test_suite": false,
        "aws_validated": false,
        "snapshot_tested": false,
        "snapshot_skipped": ""
      }
    },
    {
      "ListDocumentMetadataHistory": {
        "implemented": false,
        "availability": "",
        "internal_test_suite": false,
        "external_test_suite": false,
        "terraform_test_suite": false,
        "aws_validated": false,
        "snapshot_tested": false,
        "snapshot_skipped": ""
      }
    },
    {
      "ListDocumentVersions": {
        "implemented": false,
        "availability": "",
        "internal_test_suite": false,
        "external_test_suite": false,
        "terraform_test_suite": false,
        "aws_validated": false,
        "snapshot_tested": false,
        "snapshot_skipped": ""
      }
    },
    {
      "ListDocuments": {
        "implemented": true,
        "availability": "community",
        "internal_test_suite": false,
        "external_test_suite": false,
        "terraform_test_suite": false,
        "aws_validated": false,
        "snapshot_tested": false,
        "snapshot_skipped": ""
      }
    },
    {
      "ListInventoryEntries": {
        "implemented": false,
        "availability": "",
        "internal_test_suite": false,
        "external_test_suite": false,
        "terraform_test_suite": false,
        "aws_validated": false,
        "snapshot_tested": false,
        "snapshot_skipped": ""
      }
    },
    {
      "ListNodes": {
        "implemented": false,
        "availability": "",
        "internal_test_suite": false,
        "external_test_suite": false,
        "terraform_test_suite": false,
        "aws_validated": false,
        "snapshot_tested": false,
        "snapshot_skipped": ""
      }
    },
    {
      "ListNodesSummary": {
        "implemented": false,
        "availability": "",
        "internal_test_suite": false,
        "external_test_suite": false,
        "terraform_test_suite": false,
        "aws_validated": false,
        "snapshot_tested": false,
        "snapshot_skipped": ""
      }
    },
    {
      "ListOpsItemEvents": {
        "implemented": false,
        "availability": "",
        "internal_test_suite": false,
        "external_test_suite": false,
        "terraform_test_suite": false,
        "aws_validated": false,
        "snapshot_tested": false,
        "snapshot_skipped": ""
      }
    },
    {
      "ListOpsItemRelatedItems": {
        "implemented": false,
        "availability": "",
        "internal_test_suite": false,
        "external_test_suite": false,
        "terraform_test_suite": false,
        "aws_validated": false,
        "snapshot_tested": false,
        "snapshot_skipped": ""
      }
    },
    {
      "ListOpsMetadata": {
        "implemented": false,
        "availability": "",
        "internal_test_suite": false,
        "external_test_suite": false,
        "terraform_test_suite": false,
        "aws_validated": false,
        "snapshot_tested": false,
        "snapshot_skipped": ""
      }
    },
    {
      "ListResourceComplianceSummaries": {
        "implemented": false,
        "availability": "",
        "internal_test_suite": false,
        "external_test_suite": false,
        "terraform_test_suite": false,
        "aws_validated": false,
        "snapshot_tested": false,
        "snapshot_skipped": ""
      }
    },
    {
      "ListResourceDataSync": {
        "implemented": false,
        "availability": "",
        "internal_test_suite": false,
        "external_test_suite": false,
        "terraform_test_suite": false,
        "aws_validated": false,
        "snapshot_tested": false,
        "snapshot_skipped": ""
      }
    },
    {
      "ListTagsForResource": {
        "implemented": true,
        "availability": "community",
        "internal_test_suite": false,
        "external_test_suite": false,
        "terraform_test_suite": false,
        "aws_validated": false,
        "snapshot_tested": false,
        "snapshot_skipped": ""
      }
    },
    {
      "ModifyDocumentPermission": {
        "implemented": true,
        "availability": "community",
        "internal_test_suite": false,
        "external_test_suite": false,
        "terraform_test_suite": false,
        "aws_validated": false,
        "snapshot_tested": false,
        "snapshot_skipped": ""
      }
    },
    {
      "PutComplianceItems": {
        "implemented": false,
        "availability": "",
        "internal_test_suite": false,
        "external_test_suite": false,
        "terraform_test_suite": false,
        "aws_validated": false,
        "snapshot_tested": false,
        "snapshot_skipped": ""
      }
    },
    {
      "PutInventory": {
        "implemented": false,
        "availability": "",
        "internal_test_suite": false,
        "external_test_suite": false,
        "terraform_test_suite": false,
        "aws_validated": false,
        "snapshot_tested": false,
        "snapshot_skipped": ""
      }
    },
    {
      "PutParameter": {
        "implemented": true,
        "availability": "community",
        "internal_test_suite": false,
        "external_test_suite": false,
        "terraform_test_suite": false,
        "aws_validated": false,
        "snapshot_tested": false,
        "snapshot_skipped": ""
      }
    },
    {
      "PutResourcePolicy": {
        "implemented": false,
        "availability": "",
        "internal_test_suite": false,
        "external_test_suite": false,
        "terraform_test_suite": false,
        "aws_validated": false,
        "snapshot_tested": false,
        "snapshot_skipped": ""
      }
    },
    {
      "RegisterDefaultPatchBaseline": {
        "implemented": false,
        "availability": "",
        "internal_test_suite": false,
        "external_test_suite": false,
        "terraform_test_suite": false,
        "aws_validated": false,
        "snapshot_tested": false,
        "snapshot_skipped": ""
      }
    },
    {
      "RegisterPatchBaselineForPatchGroup": {
        "implemented": false,
        "availability": "",
        "internal_test_suite": false,
        "external_test_suite": false,
        "terraform_test_suite": false,
        "aws_validated": false,
        "snapshot_tested": false,
        "snapshot_skipped": ""
      }
    },
    {
      "RegisterTargetWithMaintenanceWindow": {
        "implemented": true,
        "availability": "community",
        "internal_test_suite": false,
        "external_test_suite": false,
        "terraform_test_suite": false,
        "aws_validated": false,
        "snapshot_tested": false,
        "snapshot_skipped": ""
      }
    },
    {
      "RegisterTaskWithMaintenanceWindow": {
        "implemented": true,
        "availability": "community",
        "internal_test_suite": false,
        "external_test_suite": false,
        "terraform_test_suite": false,
        "aws_validated": false,
        "snapshot_tested": false,
        "snapshot_skipped": ""
      }
    },
    {
      "RemoveTagsFromResource": {
        "implemented": true,
        "availability": "community",
        "internal_test_suite": false,
        "external_test_suite": false,
        "terraform_test_suite": false,
        "aws_validated": false,
        "snapshot_tested": false,
        "snapshot_skipped": ""
      }
    },
    {
      "ResetServiceSetting": {
        "implemented": false,
        "availability": "",
        "internal_test_suite": false,
        "external_test_suite": false,
        "terraform_test_suite": false,
        "aws_validated": false,
        "snapshot_tested": false,
        "snapshot_skipped": ""
      }
    },
    {
      "ResumeSession": {
        "implemented": false,
        "availability": "",
        "internal_test_suite": false,
        "external_test_suite": false,
        "terraform_test_suite": false,
        "aws_validated": false,
        "snapshot_tested": false,
        "snapshot_skipped": ""
      }
    },
    {
      "SendAutomationSignal": {
        "implemented": false,
        "availability": "",
        "internal_test_suite": false,
        "external_test_suite": false,
        "terraform_test_suite": false,
        "aws_validated": false,
        "snapshot_tested": false,
        "snapshot_skipped": ""
      }
    },
    {
      "SendCommand": {
        "implemented": true,
        "availability": "community",
        "internal_test_suite": false,
        "external_test_suite": false,
        "terraform_test_suite": false,
        "aws_validated": false,
        "snapshot_tested": false,
        "snapshot_skipped": ""
      }
    },
    {
      "StartAccessRequest": {
        "implemented": false,
        "availability": "",
        "internal_test_suite": false,
        "external_test_suite": false,
        "terraform_test_suite": false,
        "aws_validated": false,
        "snapshot_tested": false,
        "snapshot_skipped": ""
      }
    },
    {
      "StartAssociationsOnce": {
        "implemented": false,
        "availability": "",
        "internal_test_suite": false,
        "external_test_suite": false,
        "terraform_test_suite": false,
        "aws_validated": false,
        "snapshot_tested": false,
        "snapshot_skipped": ""
      }
    },
    {
      "StartAutomationExecution": {
        "implemented": false,
        "availability": "",
        "internal_test_suite": false,
        "external_test_suite": false,
        "terraform_test_suite": false,
        "aws_validated": false,
        "snapshot_tested": false,
        "snapshot_skipped": ""
      }
    },
    {
      "StartChangeRequestExecution": {
        "implemented": false,
        "availability": "",
        "internal_test_suite": false,
        "external_test_suite": false,
        "terraform_test_suite": false,
        "aws_validated": false,
        "snapshot_tested": false,
        "snapshot_skipped": ""
      }
    },
    {
      "StartExecutionPreview": {
        "implemented": false,
        "availability": "",
        "internal_test_suite": false,
        "external_test_suite": false,
        "terraform_test_suite": false,
        "aws_validated": false,
        "snapshot_tested": false,
        "snapshot_skipped": ""
      }
    },
    {
      "StartSession": {
        "implemented": false,
        "availability": "",
        "internal_test_suite": false,
        "external_test_suite": false,
        "terraform_test_suite": false,
        "aws_validated": false,
        "snapshot_tested": false,
        "snapshot_skipped": ""
      }
    },
    {
      "StopAutomationExecution": {
        "implemented": false,
        "availability": "",
        "internal_test_suite": false,
        "external_test_suite": false,
        "terraform_test_suite": false,
        "aws_validated": false,
        "snapshot_tested": false,
        "snapshot_skipped": ""
      }
    },
    {
      "TerminateSession": {
        "implemented": false,
        "availability": "",
        "internal_test_suite": false,
        "external_test_suite": false,
        "terraform_test_suite": false,
        "aws_validated": false,
        "snapshot_tested": false,
        "snapshot_skipped": ""
      }
    },
    {
      "UnlabelParameterVersion": {
        "implemented": false,
        "availability": "",
        "internal_test_suite": false,
        "external_test_suite": false,
        "terraform_test_suite": false,
        "aws_validated": false,
        "snapshot_tested": false,
        "snapshot_skipped": ""
      }
    },
    {
      "UpdateAssociation": {
        "implemented": false,
        "availability": "",
        "internal_test_suite": false,
        "external_test_suite": false,
        "terraform_test_suite": false,
        "aws_validated": false,
        "snapshot_tested": false,
        "snapshot_skipped": ""
      }
    },
    {
      "UpdateAssociationStatus": {
        "implemented": false,
        "availability": "",
        "internal_test_suite": false,
        "external_test_suite": false,
        "terraform_test_suite": false,
        "aws_validated": false,
        "snapshot_tested": false,
        "snapshot_skipped": ""
      }
    },
    {
      "UpdateDocument": {
        "implemented": true,
        "availability": "community",
        "internal_test_suite": false,
        "external_test_suite": false,
        "terraform_test_suite": false,
        "aws_validated": false,
        "snapshot_tested": false,
        "snapshot_skipped": ""
      }
    },
    {
      "UpdateDocumentDefaultVersion": {
        "implemented": true,
        "availability": "community",
        "internal_test_suite": false,
        "external_test_suite": false,
        "terraform_test_suite": false,
        "aws_validated": false,
        "snapshot_tested": false,
        "snapshot_skipped": ""
      }
    },
    {
      "UpdateDocumentMetadata": {
        "implemented": false,
        "availability": "",
        "internal_test_suite": false,
        "external_test_suite": false,
        "terraform_test_suite": false,
        "aws_validated": false,
        "snapshot_tested": false,
        "snapshot_skipped": ""
      }
    },
    {
      "UpdateMaintenanceWindow": {
        "implemented": false,
        "availability": "",
        "internal_test_suite": false,
        "external_test_suite": false,
        "terraform_test_suite": false,
        "aws_validated": false,
        "snapshot_tested": false,
        "snapshot_skipped": ""
      }
    },
    {
      "UpdateMaintenanceWindowTarget": {
        "implemented": false,
        "availability": "",
        "internal_test_suite": false,
        "external_test_suite": false,
        "terraform_test_suite": false,
        "aws_validated": false,
        "snapshot_tested": false,
        "snapshot_skipped": ""
      }
    },
    {
      "UpdateMaintenanceWindowTask": {
        "implemented": false,
        "availability": "",
        "internal_test_suite": false,
        "external_test_suite": false,
        "terraform_test_suite": false,
        "aws_validated": false,
        "snapshot_tested": false,
        "snapshot_skipped": ""
      }
    },
    {
      "UpdateManagedInstanceRole": {
        "implemented": false,
        "availability": "",
        "internal_test_suite": false,
        "external_test_suite": false,
        "terraform_test_suite": false,
        "aws_validated": false,
        "snapshot_tested": false,
        "snapshot_skipped": ""
      }
    },
    {
      "UpdateOpsItem": {
        "implemented": false,
        "availability": "",
        "internal_test_suite": false,
        "external_test_suite": false,
        "terraform_test_suite": false,
        "aws_validated": false,
        "snapshot_tested": false,
        "snapshot_skipped": ""
      }
    },
    {
      "UpdateOpsMetadata": {
        "implemented": false,
        "availability": "",
        "internal_test_suite": false,
        "external_test_suite": false,
        "terraform_test_suite": false,
        "aws_validated": false,
        "snapshot_tested": false,
        "snapshot_skipped": ""
      }
    },
    {
      "UpdatePatchBaseline": {
        "implemented": false,
        "availability": "",
        "internal_test_suite": false,
        "external_test_suite": false,
        "terraform_test_suite": false,
        "aws_validated": false,
        "snapshot_tested": false,
        "snapshot_skipped": ""
      }
    },
    {
      "UpdateResourceDataSync": {
        "implemented": false,
        "availability": "",
        "internal_test_suite": false,
        "external_test_suite": false,
        "terraform_test_suite": false,
        "aws_validated": false,
        "snapshot_tested": false,
        "snapshot_skipped": ""
      }
    },
    {
      "UpdateServiceSetting": {
        "implemented": false,
        "availability": "",
        "internal_test_suite": false,
        "external_test_suite": false,
        "terraform_test_suite": false,
        "aws_validated": false,
        "snapshot_tested": false,
        "snapshot_skipped": ""
      }
    }
  ],
  "details": {}
}